{
  "coord": {
    "lon": 30.7178,
    "lat": 36.7741
  },
  "weather": [
    {
      "id": 803,
      "main": "Clouds",
      "description": "broken clouds",
      "icon": "04n"
    }
  ],
  "base": "stations",
  "main": {
    "temp": 14.75,
    "feels_like": 14,
    "temp_min": 14.75,
    "temp_max": 14.75,
    "pressure": 1014,
    "humidity": 66,
    "sea_level": 1014,
    "grnd_level": 1004
  },
  "visibility": 10000,
  "wind": {
    "speed": 3.66,
    "deg": 15,
    "gust": 3.91
  },
  "clouds": {
    "all": 79
  },
  "dt": 1775853277,
  "sys": {
    "country": "TR",
    "sunrise": 1775791818,
    "sunset": 1775838376
  },
  "timezone": 10800,
  "id": 323776,
  "name": "Antalya Province",
  "cod": 200,
  "_last_updated_utc": "2026-04-10T20:36:27.042Z"
}